setup.py
issuetracker/__init__.py
issuetracker/admin.py
issuetracker/models.py
issuetracker.egg-info/PKG-INFO
issuetracker.egg-info/SOURCES.txt
issuetracker.egg-info/dependency_links.txt
issuetracker.egg-info/top_level.txt