Metadata-Version: 1.0
Name: issuetracker
Version: 1.0
Summary: Using the automagic django admin site to track issues.
Home-page: https://github.com/brunobord/django-mini-issue-tracker
Author: Bruno Bord
Author-email: bruno@jehaisleprintemps.net
License: Unknown
Platform: UNKNOWN
